<?xml version="1.0" encoding="UTF-8"?>
<Zusi>
<Info DateiTyp="Buchfahrplan" Version="A.3" MinVersion="A.0">
<AutorEintrag AutorID="33" AutorName="Alwin Meschede" AutorEmail="ameschede@gmx.de"/>
</Info>
<Buchfahrplan Gattung="EK" Nummer="54344" Zuglauf="Paderborn Nord - Paderborn Gbf" BR="363" Masse="300540" spMax="16.6667" Bremsh="0.8984" Laenge="172.11" LaengeLoks="10.45" kmStart="2.7767" BremsstellungZug="2">
<Datei_fpn Dateiname="Timetables\Deutschland\Paderborn_Kassel_Ruhrtalbahn\PB-KS-Ruhrtal_2013_12Uhr-24Uhr.fpn" NurInfo="1"/>
<Datei_trn Dateiname="Timetables\Deutschland\Paderborn_Kassel_Ruhrtalbahn\PB-KS-Ruhrtal_2013_12Uhr-24Uhr\EK54344.trn" NurInfo="1"/>
<UTM UTM_WE="505" UTM_NS="5705" UTM_Zone="32" UTM_Zone2="U"/>
<FplZeile FplLaufweg="71.0249">
<FplIcon FplIconNr="1"/>
<FplName FplNameText="- ZBF A 75 -"/>
<FplvMax vMax="13.8889"/>
</FplZeile>
<FplZeile FplLaufweg="73.0249">
<FplvMax vMax="13.8889"/>
<Fplkm km="-0.04"/>
</FplZeile>
<FplZeile FplLaufweg="2521.4268">
<FplNameRechts FplNameText="E 50"/>
<Fplkm km="0.2508" FplSprung="1" FplkmNeu="128.5911"/>
<FplName FplNameText="Paderborn Hbf"/>
<FplAnk Ank="2013-08-21 14:05:00" FplEintrag="1"/>
<FplAbf Abf="2013-08-21 14:05:00"/>
</FplZeile>
<FplZeile FplLaufweg="2813.1028">
<FplName FplNameText="Paderborn Hbf"/>
<Fplkm km="128.2994"/>
<FplAnk Ank="2013-08-21 14:12:00"/>
<FplAbf Abf="2013-08-21 15:02:00"/>
</FplZeile>
<FplZeile FplLaufweg="2883.252">
<FplSignaltyp FplSignaltypNr="8"/>
<Fplkm km="128.3695"/>
</FplZeile>
<FplZeile FplLaufweg="2996.0437">
<FplvMax vMax="27.7778"/>
<Fplkm km="128.4868"/>
</FplZeile>
<FplZeile FplLaufweg="3399.6843">
<FplName FplNameText="Paderborn Gbf"/>
<Fplkm km="128.8859"/>
</FplZeile>
</Buchfahrplan>
</Zusi>
