<?xml version="1.0" encoding="UTF-8"?>
<Zusi>
   <Info DateiTyp="Signal" Version="A.1" MinVersion="A.1" Beschreibung="">
      <AutorEintrag AutorID="110" AutorName="Valentin"/>
   </Info>
   <Signal>
      <SignalFrame>
         <Datei Dateiname="Signals\France\Ligne_normale\Tableaux_divers\Pancarte_arret-de-trains-du-chantier\Pancarte_arret-de-trains-du-chantier_gauche.lod.ls3"/>
      </SignalFrame>
	  <HsigBegriff HsigGeschw="-1.0000" FahrstrTyp="0"/>
      <VsigBegriff VsigGeschw="-1.0000"/>
      <MatrixEintrag Signalbild="1" MatrixGeschw="-1.0000"/>
   </Signal>
</Zusi>
